[
  {
    "from": "test",
    "text": "test",
    "date": "2025-06-05T17:10:07.413Z"
  },
  {
    "voornaam": "amber",
    "achternaam": "Schalker",
    "email": "amschalker@gmail.com",
    "text": "test"
  },
  {
    "voornaam": "Amber",
    "achternaam": "Schalker",
    "email": "amschalker@gmail.com",
    "text": "test 2\r\n"
  },
  {
    "voornaam": "Amber",
    "achternaam": "Schalker",
    "email": "amschalker@gmail.com",
    "text": "test"
  },
  {
    "voornaam": "Amber",
    "achternaam": "Schalker",
    "email": "amschalker@gmail.com",
    "text": "test 3\r\n"
  },
  {
    "voornaam": "Amber",
    "achternaam": "Schalker",
    "email": "amschalker@gmail.com",
    "text": "test 3\r\n"
  },
  {
    "voornaam": "amber",
    "achternaam": "Schalker",
    "email": "amschalker@gmail.com",
    "text": "testttttt"
  },
  {
    "voornaam": "test",
    "achternaam": "test",
    "email": "amschalker@gmail.com",
    "text": "test"
  },
  {
    "voornaam": "ss,s,",
    "achternaam": "ksks",
    "email": "amschalker@gmail.com"
  },
  {
    "voornaam": "test",
    "achternaam": "test",
    "email": "amschalker@gmail.com"
  },
  {
    "voornaam": "Amber",
    "achternaam": "Schalker",
    "email": "amschalker@gmail.com"
  },
  {
    "voornaam": "test",
    "achternaam": "Schalker",
    "email": "amschalker@gmail.com",
    "bericht": "yessssss"
  }
]